artis/__init__.py
artis-0.0.0.dist-info/METADATA
artis-0.0.0.dist-info/WHEEL
artis-0.0.0.dist-info/top_level.txt
artis-0.0.0.dist-info/RECORD
