Metadata-Version: 2.1
Name: artis
Version: 0.0.0
Summary: Scientific Methods Software Package
Home-page: https://github.com/scimet/artis
Author: Joaquín Otón
License: UNKNOWN
Platform: UNKNOWN
Classifier: Programming Language :: Python :: 3
Classifier: Operating System :: OS Independent
Requires-Python: >=3.7
Requires-Dist: numpy
Requires-Dist: pandas
Requires-Dist: numba
Requires-Dist: docopt
Requires-Dist: scipy
Requires-Dist: mrcfile
Requires-Dist: tqdm
